aisports/__init__.py
aisports/checkers.py
aisports-0.30.dist-info/METADATA
aisports-0.30.dist-info/WHEEL
aisports-0.30.dist-info/top_level.txt
aisports-0.30.dist-info/RECORD
