Metadata-Version: 2.1
Name: aisports
Version: 0.30
Summary: AISports Python wrapper
Home-page: https://aisports.ai
Author: Artur Luik
Author-email: artur.luik@gmail.com
License: UNKNOWN
Platform: UNKNOWN
Requires-Dist: websockets
Requires-Dist: requests
